{
    "AX":{
        "error":0.0046261117,
        "error_type":"SEM",
        "filter_outliers_dict":{
            "filter_outliers":true,
            "iterations":1,
            "std_devs":2
        },
        "fit":"average",
        "value":0.0088488187
    },
    "CDD":{
        "error":0.0000260801,
        "error_type":"SEM",
        "filter_outliers_dict":{
            "filter_outliers":true,
            "iterations":1,
            "std_devs":10
        },
        "fit":"average",
        "value":0.0003291478
    },
    "H1":{
        "error":0.0049745789,
        "error_type":"SEM",
        "filter_outliers_dict":{
            "filter_outliers":true,
            "iterations":1,
            "std_devs":2
        },
        "fit":"average",
        "value":0.0593138114
    },
    "H2":{
        "error":0.0146888758,
        "error_type":"SEM",
        "filter_outliers_dict":{
            "filter_outliers":true,
            "iterations":1,
            "std_devs":2
        },
        "fit":"average",
        "value":0.0090340312
    },
    "L1":{
        "error":0.00286167,
        "error_type":"SEM",
        "filter_outliers_dict":{
            "filter_outliers":true,
            "iterations":1,
            "std_devs":2
        },
        "fit":"average",
        "value":-0.0416047071
    },
    "L2":{
        "error":0.0057372601,
        "error_type":"SEM",
        "filter_outliers_dict":{
            "filter_outliers":true,
            "iterations":1,
            "std_devs":2
        },
        "fit":"average",
        "value":-0.0381699217
    }
}