{
    "Ar36":{
        "error":0.0006587765,
        "error_type":"SEM",
        "filter_outliers_dict":{
            "filter_outliers":true,
            "iterations":1,
            "std_devs":2
        },
        "fit":"Parabolic",
        "value":0.1039527959
    },
    "Ar37":{
        "error":0.00634991,
        "error_type":"SEM",
        "filter_outliers_dict":{
            "filter_outliers":true,
            "iterations":1,
            "std_devs":2
        },
        "fit":"linear",
        "value":10.7507597413
    },
    "Ar38":{
        "error":0.0025957806,
        "error_type":"SEM",
        "filter_outliers_dict":{
            "filter_outliers":true,
            "iterations":1,
            "std_devs":2
        },
        "fit":"linear",
        "value":0.2487941915
    },
    "Ar39":{
        "error":0.0116410815,
        "error_type":"SEM",
        "filter_outliers_dict":{
            "filter_outliers":true,
            "iterations":1,
            "std_devs":2
        },
        "fit":"Parabolic",
        "value":19.7662001416
    },
    "Ar40":{
        "error":0.0234678269,
        "error_type":"SEM",
        "filter_outliers_dict":{
            "filter_outliers":true,
            "iterations":1,
            "std_devs":2
        },
        "fit":"Parabolic",
        "value":284.9788620023
    },
    "Ar41":{
        "error":0.0124863222,
        "error_type":"SEM",
        "filter_outliers_dict":{
            "filter_outliers":true,
            "iterations":1,
            "std_devs":2
        },
        "fit":"linear",
        "value":0.0546796906
    }
}